{"date":"2023-02-15T11:00:03.987Z","data":[{"id":"XOQJM9YjGoE","title":"Sorry BaBu | the mridul | Pragati | Nitin","categoryId":"23","channelId":"UC0zXnLIFedO97pFsyMxZcFg","channelTitle":"The MriDul","tags":["the mridul","the mridul new video","the mridul comedy","nitin mridul","nitin mridul ki video","pragati","pragati new video","mastani ki comedy","comedy video","funny video","new comedy video","nitin mridul comedy","trending video","valentine day comedy","valentine day","setting se meeting","Sorry baBu","viral video","most funny video","entertainment"],"thumbnails":"https://i.ytimg.com/vi/XOQJM9YjGoE/sddefault.jpg","publishedAt":"2023-02-14T13:40:00Z"},{"id":"Tr8AS-a4AOc","title":"Sasta Biig Bosss 2 | Parody | Ashish Chanchlani","categoryId":"23","channelId":"UC7eHZXheF8nVOfwB2PEslMw","channelTitle":"ashish chanchlani vines","tags":["ashish chanchlani","ashish chanchlani new video","ashish chanchlani new","ashish new video","ashish chanchlani sasta big boss","bigg boss","bigg boss 16","ashish chanchlani sasta bigg boss","ashish chanchlani bigg boss video","bigg boss funny video","abdu funny","bigg boss finale","bigg boss 16 funny moments","bigg boss winner","ashish chanchlani vines","acv","teddy bear funny scene","mc stan finale","shiv thakare","bigg boss funny task","bigg bosss funny","badbu","badbu ashish","bigg boss spoof"],"thumbnails":"https://i.ytimg.com/vi/Tr8AS-a4AOc/sddefault.jpg","publishedAt":"2023-02-13T07:40:01Z"},{"id":"P8CoOBa8QT0","title":"Short Highlights | Karachi Kings vs Peshawar Zalmi | Match 2 | HBL PSL 8 | MI2T","categoryId":"17","channelId":"UCpNzXJ5jpcJojC5mHQvGA8w","channelTitle":"Pakistan Super League","tags":["Short Highlights","Peshawar Zalmi","Karachi Kings","Peshawar Zalmi Batting","Match 2","Karachi Kings Batting","Karachi Kings vs Peshawar Zalmi","Karachi vs Peshawar","Karachi Kings vs Peshawar Zalmi Highlights","Karachi vs Peshawar Live","Peshawar Zalmi Batting Highlights","Karachi Kings Batting Highlights","HBL PSL 8","HBL PSL 8 Live","Karachi Kings vs Peshawar Zalmi Match","Peshawar vs Karachi Highlights","Peshawar vs Karachi Matches"],"thumbnails":"https://i.ytimg.com/vi/P8CoOBa8QT0/sddefault.jpg","publishedAt":"2023-02-14T21:13:36Z"},{"id":"YCmDB-pyG9A","title":"Badhu Beshare | ବଧୂ ବେଶରେ | Official Video | Rupa & Pintu, Humane Sagar, Nibedan | Sidharth Music","categoryId":"10","channelId":"UCl14vsKo26SS8OcHedmmaPw","channelTitle":"Sidharth Music","tags":["sidharth music","siddharth music","sidharth music channel","sidharth music new odia song","sidharth music new video","best odia song","new odia album song","sarthak music best song","odia album song new","sarthak music album song","odia music video","oriya song","odia song new","odia song video","Badhu Besha","Humane Sagar","Rupa Pintu","RupaPin2khushiexpress","Rupa Pintu new music video","Badhu Besare Rupa Pintu","Rupa Pintu Badhu Besare","Badhu Besare","Badhu besa"],"thumbnails":"https://i.ytimg.com/vi/YCmDB-pyG9A/sddefault.jpg","publishedAt":"2023-02-14T04:30:10Z"},{"id":"oqcXT3tkZD0","title":"(M.C.K) Macharla Chunaav Kshetra New Released Full Hindi Dubbed Movie | Nithiin, Krithi Shetty","categoryId":"1","channelId":"UCX_uPA_dGf7wXjuMEaSKLJA","channelTitle":"Aditya Movies","tags":["Macharla ChunaavKshetra","MCK","Macharla Chunaav Kshetra hindi dubbed movie","Nithiin","macherla niyojakavargam full movie in hindi","nithin all movies in hindi dubbed","macharla full movie in hindi","south movie2023","hindi dubbed movies","mck full hindi dubbed movie","South Indian movies dubbed in hindi full movie 2022new","New Movie","South movie","Hindi Movie","new south movie","aditya movies","krithishetty","mck movie hindi dubbed download","nithin krithi shetty new movie","krithi shetty movies"],"thumbnails":"https://i.ytimg.com/vi/oqcXT3tkZD0/sddefault.jpg","publishedAt":"2023-02-10T13:30:08Z"},{"id":"67glWzLrcSI","title":"Diary Milk VS Jolo Chip Challenge | Valentine's Day Special Vlog | M4 Tech |","categoryId":"24","channelId":"UC4rKvhYJIN-2Pe6zGtxtIqw","channelTitle":"M4 TECH VLOG","thumbnails":"https://i.ytimg.com/vi/67glWzLrcSI/sddefault.jpg","publishedAt":"2023-02-14T15:18:20Z"},{"id":"pjSxOnCkHIA","title":"Cheenk | Stand-Up Comedy | Aakash Gupta","categoryId":"23","channelId":"UCAYum5hCyfkSH5T3vSD_kwQ","channelTitle":"Aakash Gupta","tags":["standupcomedy","comedy","Aakash gupta","Akash gupta","Akash gupta comedy","Aakash gupta comedy","Cheenk","Standup"],"thumbnails":"https://i.ytimg.com/vi/pjSxOnCkHIA/sddefault.jpg","publishedAt":"2023-02-13T17:40:08Z"},{"id":"CQDXtD2HJAs","title":"LOVE AGAIN - Official Trailer (HD)","categoryId":"1","channelId":"UCz97F7dMxBNOfGYu3rx8aCw","channelTitle":"Sony Pictures Entertainment","thumbnails":"https://i.ytimg.com/vi/CQDXtD2HJAs/sddefault.jpg","publishedAt":"2023-02-14T17:00:15Z"},{"id":"scpOtIw1mCY","title":"Exclusive Interview With The \"King\" Of Tripura Who's Demanding A Separate State || Ft. Anil Sharda.","categoryId":"25","channelId":"UC6JEz6BKg7hX7idKecN7QYA","channelTitle":"Jist","tags":["Pradyot Debburman Interview","pradyot debburman","tripura polls","royal prince pradyot manikya deb burman","pradyot kishor interview","letest interview pradyot debburman interview","tripura assembly election 20223","tripura election 2023","tripura election result","greater tripura land","tripura land","tripura motha","what is greater tripura land","Anil sharda","tripura prince","tripura election news","pradyot kishore manikya wife","kirit pradyot deb barman","pradyot manikya debbarma"],"thumbnails":"https://i.ytimg.com/vi/scpOtIw1mCY/sddefault.jpg","publishedAt":"2023-02-14T13:57:19Z"},{"id":"xvkAYRm73oI","title":"YouTube ന്റെ Vintage സമ്മാനം🥰","categoryId":"22","channelId":"UCkJfmb163NsCn5RilDm7Q6g","channelTitle":"Karthik Surya","tags":["karthik surya","malayalam vlog","kerala","kerala vlog","trivandrum","ernakulam","malayalam entertainment","entertainment","comedy","peoples and blog"],"thumbnails":"https://i.ytimg.com/vi/xvkAYRm73oI/sddefault.jpg","publishedAt":"2023-02-14T13:30:21Z"},{"id":"RniSiUXdyCs","title":"വിവാഹശേഷം പ്രവീണിന്റെ വീട്ടിലേക്കു പോകാൻ കൈ പിടിച്ച് ഐഷു 😍👌 Trasgender Praveen Rishana Aishu wedding","categoryId":"22","channelId":"UC1lj6vxt1OEFZ4icxmBBJKA","channelTitle":"Variety Media Live","thumbnails":"https://i.ytimg.com/vi/RniSiUXdyCs/sddefault.jpg","publishedAt":"2023-02-14T10:44:42Z"},{"id":"gUZ0dpv3j94","title":"EXCLUSIVE: Valentine’s Day Special - Shubha Poonja & Sumanth’s CUTEST Interview With Anushree","categoryId":"24","channelId":"UCwYtWLSX11QpRCJSYNpHyKA","channelTitle":"Anushree Anchor","tags":["Anchor anushree","anushree anchor","anushree anchor dance","anushree anchor channel","anushree anchor interview","anushree anchor youtube","anushree anchor videos","kannada anchor anushree","anchor anushree youtube channel","anushree recent interview","anchor anushree trending video","anushree interview video","shubha punja interview with anushree","couple interview","anushree interview","Shubha punja interview","shubha punja","shubha punja husband","valentine's day interview","anchor anushree"],"thumbnails":"https://i.ytimg.com/vi/gUZ0dpv3j94/sddefault.jpg","publishedAt":"2023-02-14T12:30:08Z"},{"id":"5PPijhzZfTw","title":"He din’t know what he did wrong !!! | Pearle Maaney | Srinish Aravind","categoryId":"24","channelId":"UCeALltNJ6GDNRwA0B7clXyA","channelTitle":"Pearle Maaney","tags":["pearle","pearle maaney","pearly","srinish","srinish aravind","pearlish","chellakuttiye","chellakannane","tamil song","bigg boss","bigg boss tamil","bigg boss malayalam","bollywood actress","ludo movie","a day in our life","surprise","visit","tamil","tamil paiyan","nila srinish","nila","nila baby","vlogger","lifestyle","youtuber","memories","goa","#ValentinesDay","#Love","#CoupleGoals","#Relationships","#Romance","#DateNight","#Heartfelt","#GiftIdeas","#LoveIsInTheAir","#HeartwarmingMoments","#LoveStory","#ValentinesDaySpecial"],"thumbnails":"https://i.ytimg.com/vi/5PPijhzZfTw/sddefault.jpg","publishedAt":"2023-02-14T10:30:05Z"},{"id":"3Ec1Q_7O3tQ","title":"Sapta Sagaradaache Ello | Official Teaser 2 | Rakshit Shetty | Rukmini | Chaithra | Hemanth M Rao","categoryId":"1","channelId":"UCvBaJ5MfXVKfSiKP2beaNvw","channelTitle":"Paramvah Studios","tags":["Sapta Sagaradaache Ello","SSE Teaser","Saptha Sagaradaache Ello","kannada teaser","Saptha Sagaradaache Ello - Official Teaser","Saptha Sagaradaache Ello movie","Saptha Sagaradaache Ello new movie","Saptha Sagaradaache Ello teaser","Saptha Sagaradaache Ello kannada movie","Saptha Sagaradaache Ello film","Saptha Sagaradaache Ello movie kannada","kannada","New movie","Kannada new teasers","Rakshit Shetty","Rukmini Vasanth","Hemanth M Rao","saptha sagaradache ello"],"thumbnails":"https://i.ytimg.com/vi/3Ec1Q_7O3tQ/sddefault.jpg","publishedAt":"2023-02-14T16:06:44Z"},{"id":"RDbH9XhnmIg","title":"Tarak Mehta Ka Ooltah Chashma | Tappu Is Back! Tappu Sena On Welcoming New Tappu In The Show & More","categoryId":"24","channelId":"UCmpszHHayYGRtBiCZTs1M1w","channelTitle":"FIFAFOOZ TV","thumbnails":"https://i.ytimg.com/vi/RDbH9XhnmIg/sddefault.jpg","publishedAt":"2023-02-14T13:48:08Z"},{"id":"glQj3wQv85U","title":"How Well Do We Know Each other | Vithika Sheru | Varun Sandesh | EP - 122","categoryId":"24","channelId":"UC1EgiFrHCSCPT2-zHvRvF2A","channelTitle":"Vithika Sheru","thumbnails":"https://i.ytimg.com/vi/glQj3wQv85U/sddefault.jpg","publishedAt":"2023-02-14T08:13:10Z"},{"id":"VHoCE-UOYPQ","title":"Couples Sothanaigal | Valentines Day Special | Sothanaigal","categoryId":"23","channelId":"UCD1CuflSWxeAGVOwicubsWw","channelTitle":"Sothanaigal","tags":["sothanaigal","sothanaigal in tamil","sothanaigal channel","#sothanaigal","sothanaigal new video","sothanaigal youtube channel","sothanaigal new episode","sothanaigal new","sothanaigal videos","sothanaigal video","sothanaigal micset","micset sothanaigal","tamil comedy","sothanaigal comedy","couples sothanaigal","lovers sothanaigal","valentinesday comedy","couple sothanaigal","Sothanaigal","Sothanaigal new","Sothanaigal latest","Couplw sothanaigal","Valentines day sothanaigal","New sothanaigal"],"thumbnails":"https://i.ytimg.com/vi/VHoCE-UOYPQ/sddefault.jpg","publishedAt":"2023-02-14T11:30:09Z"},{"id":"9vwaD9cHLNw","title":"The Flash – Official Trailer","categoryId":"1","channelId":"UCiifkYAs_bq1pt_zbNAzYGg","channelTitle":"DC","tags":["Andy Muschietti","Barry Allen","Batman","Ben Affleck","Bruce Wayne","Coming Soon","DC","DC Comics","DC Extended Universe","Ezra Miller","Film","Film Trailer","Film Warner","General Zod","Iris West","Kiersey Clemons","Michael Keaton","Michael Shannon","Movie","Multiverse","Official Trailer","Super Hero","Superhero","The Batman","The Flash","Trailer","Trailer 2023","WB","Warner","Warner Bros","Warner Brothers"],"thumbnails":"https://i.ytimg.com/vi/9vwaD9cHLNw/sddefault.jpg","publishedAt":"2023-02-12T23:00:36Z"},{"id":"DuQHfO-cnsM","title":"Eruma Saani | \"A\" Bachelor Villas | EP - 2 | 2023 Tamil Comedy Web Series |","categoryId":"23","channelId":"UCPyFYlqbkxkWX_dWCg0eekA","channelTitle":"Eruma Saani","tags":["Eruma Saani","Tamil Comedy Videos","Films","Movies","Harija","Short","Film","Eruma Sani","Eruma Saani Videos","Eruma Saani Short Film","Eruma Saani Comedy","Eruma Saani Harija"],"thumbnails":"https://i.ytimg.com/vi/DuQHfO-cnsM/sddefault.jpg","publishedAt":"2023-02-13T13:09:34Z"},{"id":"sXhsOdOdMOw","title":"Dream Girl is Back | Dream Girl 2 | Ayushmann Khurrana | Ananya Panday | Ektaa K | #7KoSaathMein","categoryId":"24","channelId":"UCSHLoG-bXj1aVA2T5y8t84A","channelTitle":"BalajiMotionPictures","thumbnails":"https://i.ytimg.com/vi/sXhsOdOdMOw/sddefault.jpg","publishedAt":"2023-02-13T16:40:07Z"},{"id":"ef88EbDqjyY","title":"Ethirneechal - Preview | Full EP free on SUN NXT | 14 February 2023  | Sun TV | Tamil Serial","categoryId":"24","channelId":"UCBnxEdpoZwstJqC1yZpOjRA","channelTitle":"Sun TV","tags":["Ethirneechal","Ethirneechal serial","Ethirneechal Preview","Ethirneechal serial Preview","Ethirneechal today","Ethirneechal sun tv serial","Sun TV Serial","Sun TV Serials","sun tv tamil serial","SunTV Serial Today","sun tv serial today","Sun tv full episodes","Sun tv tamil full episodes","Sun tv tamil shows","sun tv shows","Tamil Serials","tamil serials sun tv","Tamil Serial episodes","Jovita","Ambika","jovita livingston"],"thumbnails":"https://i.ytimg.com/vi/ef88EbDqjyY/sddefault.jpg","publishedAt":"2023-02-14T15:54:39Z"},{"id":"C8EAt7nxT9A","title":"CARS DRAG RACE || Sumit Bhyan","categoryId":"24","channelId":"UCexMUgLtWZbz5-yWIBNMuxA","channelTitle":"Sumit Bhyan","tags":["sumit bhyan","sumit bhyan new video","comedy video","funny video","valentines day special","car race","drag race","safari vs thar","thar lovers","creta vs thar vs safari","aura vs thar","honda city vs thar","mercedies vs thar","sumit bhyan car race","sumit bhyan ki thar","fun","family comedy","car lovers"],"thumbnails":"https://i.ytimg.com/vi/C8EAt7nxT9A/sddefault.jpg","publishedAt":"2023-02-14T09:40:17Z"},{"id":"eI1SBbNugfc","title":"Tarak Mehta Ka Ooltah Chashma New Tappu Entry With Jethalal - Full Interview - Sony Sab","categoryId":"24","channelId":"UCtO0JBGfHmBRRadsEdzlJng","channelTitle":"BollywoodFlash","tags":["Tarak Mehta Ka Ooltah Chashma New Tappu Entry With Jethalal - Full Interview - Sony Sab","New Tapu Entry In Tarak Mehta ka ooltah chashma","Sony Sab"],"thumbnails":"https://i.ytimg.com/vi/eI1SBbNugfc/sddefault.jpg","publishedAt":"2023-02-14T12:51:47Z"},{"id":"1rNzo03LLLI","title":"Parumala Cheruvile Video Song 4K | Spadikam | Mohanlal | Urvashi | K. S. Chithra","categoryId":"1","channelId":"UCN8O3J_z9fdoF1xrYK89uOQ","channelTitle":"Matinee Now","tags":["parumala cheruvile","parumala cheruvile song","Parumala Cheruvile Spadikam Malayalam Audio Song","KS Chithra","spadikam songs","parumala cheruvile song new","parumala cheruvile song 4k","spadikam all songs","spadikam movie song","spadikam movie","spadikam","spadikam new","parumala cheruvile new song"],"thumbnails":"https://i.ytimg.com/vi/1rNzo03LLLI/sddefault.jpg","publishedAt":"2023-02-14T12:30:08Z"},{"id":"tyBJioe8gOs","title":"Kiara & Sidharth | Ranjha | The Wedding Filmer","categoryId":"24","channelId":"UCmsd11GSKyWz472NFo4Yz4w","channelTitle":"The Wedding Filmer","tags":["The","Wedding","Filmer","TWF","Vishal","Punjabi","Zara","Chowdhary","Indian","Films","Marriage","Bride","Groom","Family","Friends","Love","Story","Romance","Real","Happy","Ending","Perfect","Couple"],"thumbnails":"https://i.ytimg.com/vi/tyBJioe8gOs/sddefault.jpg","publishedAt":"2023-02-10T07:01:15Z"},{"id":"MJ7720O0s9M","title":"NEW! Taarak Mehta Ka Ooltah Chashmah - Ep 3694 - 14 Feb 2023 - Teaser","categoryId":"24","channelId":"UC6-F5tO8uklgE9Zy8IvbdFw","channelTitle":"Sony SAB","tags":["तारक मेहता","Ooltah Chashmah","sab tv channel","sab tv serial","taarak mehta latest episodes","taarak mehta ka ooltah chashmah","hindi comedy show","sab tv funny show","taarak new episode","ulta chashma","tarak mehta ka ultah chashma","taarak full episode","comedy","taarak mehta ep 3694","jethalal funny","taarak mehta episode","tmkoc todays episode","taark mehta new episodes","tmkoc teaser today","tmkoc new taarak mehta","dilip joshi","dilip joshi jethalal","latest episode of tmkoc","mehta sahab"],"thumbnails":"https://i.ytimg.com/vi/MJ7720O0s9M/sddefault.jpg","publishedAt":"2023-02-14T15:30:05Z"},{"id":"GneOulSQU3c","title":"Bigg Boss 16 Promo: BB 16 Winning Moment Of MC Stan | Bigg Boss 16 Winner Bana Stan | Full Video","categoryId":"24","channelId":"UC2tRhjkebu5aSo0IYcTtX2Q","channelTitle":"pressnews tv","tags":["bigg boss 16 winner","bigg boss 16 finale","bigg boss grand finale full episode","bb 16 grand finale","bigg boss 16 grand finale","bigg boss 16","bigg boss 16 today episode","bigg boss 16 Full Episode","BB 16 Fight","Bigg Boss 16 13th February 2023","BB16 13 February 2023 Full Episode","bigg boss 16 today episode full","colors tv","Bigg Boss 16 on Voot","bigg boss 16 salman khan","bb 16 promo","bigg boss 16 update","salman khan","Mc Stan","priyanka choudhary","shiv thakare"],"thumbnails":"https://i.ytimg.com/vi/GneOulSQU3c/sddefault.jpg","publishedAt":"2023-02-12T19:14:52Z"},{"id":"_wJI1R4WdmE","title":"First pregnancy/Second pregnancy","categoryId":"22","channelId":"UCKQ_PSYYYL_rjWnWZ4m2THg","channelTitle":"Enthuvayith(എന്തുവായിത്)","thumbnails":"https://i.ytimg.com/vi/_wJI1R4WdmE/sddefault.jpg","publishedAt":"2023-02-13T13:28:52Z"},{"id":"HjBo--1n8lI","title":"Rihanna’s FULL Apple Music Super Bowl LVII Halftime Show","categoryId":"17","channelId":"UCDVYQ4Zhbm3S2dlz7P1GBDg","channelTitle":"NFL","tags":["NFL","Football","American Football","sport","sports"],"thumbnails":"https://i.ytimg.com/vi/HjBo--1n8lI/sddefault.jpg","publishedAt":"2023-02-13T03:58:18Z"},{"id":"WJKluiMOs8Y","title":"Hiphop Tamizha - Poi Poi Poi | Official music video","categoryId":"10","channelId":"UC3Izrk2fUSIEwdcH0kNdzeQ","channelTitle":"HiphopTamizha","tags":["hiphoptamizha","jeeva","poipoipoi","trending","youtube","music","#1","views","social","independentmusic","musicvideo","tamil","varisu","thunivu","leo","thalapathy67","lokeshkanagaraj","behindwoods","irfanviews","aarifmindvoice"],"thumbnails":"https://i.ytimg.com/vi/WJKluiMOs8Y/sddefault.jpg","publishedAt":"2023-02-14T12:00:10Z"},{"id":"7kevjMfVf88","title":"Mangli | Shivaratri Song 2023 | Bam Bam Bhole | Promo | Sudhala Ashokteja | Prashanth R Vihari","categoryId":"10","channelId":"UC91m634trv4XQcJzOWQo4qQ","channelTitle":"Mangli Official","tags":["Mangli","Shivaratri Song 2023","Bam Bam Bhole","Sudhala Ashokteja","Prashanth R Vihari","Shivaratri song promo","Mangli songs","Mangli singer","Shiva songs","Shivaratri song","Isha","Isha foundation","Isha songs","Telugu song","mangli songs","mangli latest songs","mangli songs telugu","shivratri song","shivaratri songs telugu"],"thumbnails":"https://i.ytimg.com/vi/7kevjMfVf88/sddefault.jpg","publishedAt":"2023-02-12T12:02:04Z"},{"id":"yM4UrBtUlbM","title":"Our Morning To Evening Routine 🥰 | Suhana | Basheer Bashi | Mashura","categoryId":"22","channelId":"UC4U5j8zZxVT9xYfXSDKN7aQ","channelTitle":"Suhana Basheer","thumbnails":"https://i.ytimg.com/vi/yM4UrBtUlbM/sddefault.jpg","publishedAt":"2023-02-11T03:24:38Z"},{"id":"1uDl6cjH6Mc","title":"FAST X | Official Hindi Trailer (Universal Studios) - HD","categoryId":"1","channelId":"UCobkbYYx90aDf_oMxwni0bQ","channelTitle":"Universal Pictures India","thumbnails":"https://i.ytimg.com/vi/1uDl6cjH6Mc/sddefault.jpg","publishedAt":"2023-02-10T16:03:26Z"},{"id":"WRELhO1ERnE","title":"NEW! Ep 3694 - Gokuldham Mein Bhoot?! | Taarak Mehta Ka Ooltah Chashmah | तारक मेहता","categoryId":"23","channelId":"UCnSFZ-olBoLGLRUS_3RI2Aw","channelTitle":"Taarak Mehta Ka Ooltah Chashmah","tags":["Taarak Mehta Ka Ooltah Chashmah","तारक मेहता","hindi comedy show","taarak mehta funny","popatlal comedy","taarak mehta comedy","taarak mehta comedy scenes","bhide comedy scenes","jethalal babita funny","funny taarak mehta videos","jethalal","babita","tmkoc","tapu sonu","daya","jetha bhide","jetha daya","tapu sena","taarak episode","tmkoc latest episode","tarak mehta ka ulta chashma","taarak mehta ka ulta chashma","तारक मेहता का उल्टा चश्मा","tarak mehta","जेठालाल","tarak mehta new episode","જેઠાલાલ","bhoot"],"thumbnails":"https://i.ytimg.com/vi/WRELhO1ERnE/sddefault.jpg","publishedAt":"2023-02-14T15:30:16Z"},{"id":"X-5vgEYoue4","title":"Gun Gun | Ghar Banduk Biryani | Nagraj Manjule, Akash T, Sayali | Ashish, Kavita, AV Prafullachandra","categoryId":"10","channelId":"UCf40kH47yvowumzzK9LVKKg","channelTitle":"Zee Music Marathi","tags":["Gun Gun Song","Gungun Song","Gun Gun Video Song","Gun Gun Marathi Song","Gun Gun New Song","Ghar Banduk Biryani","Ghar Banduk Biryani Movie Song","Ghar Banduk Biryani Marathi Songs","Ghar Banduk Biryani Marathi Movie","Ghar Banduk Biryani Akash Thosar","Ghar Bandook Biryani","New Marathi Song","Latest Marathi Song","New Love Song","Nagraj Manjule","Akash Thosar","Marathi Movies","best of marathi songs","marathi hit songs","superhit marathi song","gun gun marathi song","new marathi love song"],"thumbnails":"https://i.ytimg.com/vi/X-5vgEYoue4/sddefault.jpg","publishedAt":"2023-02-13T12:30:01Z"},{"id":"ot4oFfE_R4A","title":"Rhea Ripley and Dominik Mysterio crash Rey Mysterio’s Valentine’s Day dinner","categoryId":"17","channelId":"UCJ5v_MCY6GNUBTO8-D3XoAg","channelTitle":"WWE","tags":["Angie Mysterio","Dominik Mysterio","Rey Mysterio","Rhea Ripley","superstars","world wrestling entertainment","wrestle","wrestler","wrestling","wwe","wwe 2021","مصارعه","कुश्ती","डब्लू डब्लू ई","पहलवान","मैच","व्यावसायिक कुश्ती","सुपरस्टार","rhea ripley and dominik mysterio","rhea ripley and dominik","rhea ripley and dominik mysterio edits","dominik mysterio and rey mysterio"],"thumbnails":"https://i.ytimg.com/vi/ot4oFfE_R4A/sddefault.jpg","publishedAt":"2023-02-15T00:00:37Z"},{"id":"SI0qSCKiMZQ","title":"Ethirneechal - Promo | 15 Feb 2023 | Sun TV Serial | Tamil Serial","categoryId":"24","channelId":"UCBnxEdpoZwstJqC1yZpOjRA","channelTitle":"Sun TV","tags":["Ethirneechal","Ethirneechal serial","Ethirneechal promo","Ethirneechal today","Ethirneechal serial today","Ethirneechal sun tv serial","Sun TV Serial","Sun TV Serials","sun tv tamil serial","SunTV Serial Today","sun tv serial today","Sun tv full episodes","Sun tv tamil full episodes","Sun tv tamil shows","sun tv shows","Tamil Serials","tamil serials sun tv","Tamil Serial episodes"],"thumbnails":"https://i.ytimg.com/vi/SI0qSCKiMZQ/sddefault.jpg","publishedAt":"2023-02-14T16:14:32Z"},{"id":"TfgTM5MA2XA","title":"Happy Valentines!! | Aashna Hegde","categoryId":"1","channelId":"UC9ymk0wX9xgrlYY_1aU31yA","channelTitle":"Aashna Hegde","tags":["valentinesday","cooking","datenight","ashnahegde","addykumar","addyshna","surprise"],"thumbnails":"https://i.ytimg.com/vi/TfgTM5MA2XA/sddefault.jpg","publishedAt":"2023-02-14T14:30:09Z"},{"id":"2jPc392W7xs","title":"Iss Pyar Ko Kya Naam Doon? | Kya hogi Arnav aur Khushi ki suhaagraat?","categoryId":"24","channelId":"UC-LPIU24bQXVljUXivKEeRQ","channelTitle":"StarPlus","tags":["Romantic","Comedy","Magic","Dance","Emotional","Drama","Song","Dialogue","Dhara","Nazar","episode","highlights","full episodes","special","funny","Star Plus","Plus","Rishta Wahi Baat Nayi","hotstar","shorts","family","family comedy","comedy drama","best drama","best comedy","best emotional","horror","horror show","इस","प्यार","को","क्या","नाम","दूँ?","romance","khushi","arnav","romantic","moments","iss","pyaar","ko","kyaa","naam","doon","barun","sobti","sanaya","irani","popular serial","trending serial","hindi serial","kya hogi arnav","aur khushi ki suhaagraat"],"thumbnails":"https://i.ytimg.com/vi/2jPc392W7xs/sddefault.jpg","publishedAt":"2023-02-14T13:26:26Z"},{"id":"aQ78U8iXukk","title":"Lashkare | Yo Yo Honey Singh | Full Song | Rupan Bal","categoryId":"10","channelId":"UC1KonH1j8WMhc5cT6Bp7NtA","channelTitle":"Yo Yo Honey Singh","tags":["honey singh","yo yo honey singh","alfaaz","mafia mundeer records","punjabi","bollywood","rap","punjabi rap. hindi rap","most watched artist","latest songs","latest bollywood songs","latest punjabi songs","latest hindi songs","2013","dope shope","angrezi beat","brown rang","satan","bring me back","bebo","new bollywood songs 2023","romantic hindi songs","hip hop song","Lashkare","hits of yo yo honey singh","indie songs","#shorts","new hindi song","viral song","official song","#TikTok"],"thumbnails":"https://i.ytimg.com/vi/aQ78U8iXukk/sddefault.jpg","publishedAt":"2023-02-10T06:39:39Z"},{"id":"CP6AV7lfViI","title":"Police Sothanaigal | Micset","categoryId":"23","channelId":"UC5EQWvy59VeHPJz8mDALPxg","channelTitle":"Mic Set","tags":["micset","mic set","micset sothanaigal","sothanaigal","mind voice sothanaigal","mic set sothanaigal","sothanaigal micset","mic set comedy","mike set","micset sriram","micset new episodes","mic set videos","micset sothanaigal in tamil","#micset","mic set mind voice","micset videos","micset channel tamil","mic set channel tamil","mic set in tamil","mic set video","micset latest episode","micset in tamil","police sothanaigal","police","police comedy","comedy video","Police","Police sothanaigal","Micset new"],"thumbnails":"https://i.ytimg.com/vi/CP6AV7lfViI/sddefault.jpg","publishedAt":"2023-02-09T09:45:10Z"},{"id":"JChWqe0CzaA","title":"நீயெல்லாம் மனுசனா யா.. 😡🤬| Chellamma - Episode Preview","categoryId":"24","channelId":"UCvrhwpnp2DHYQ1CbXby9ypQ","channelTitle":"Vijay Television","thumbnails":"https://i.ytimg.com/vi/JChWqe0CzaA/sddefault.jpg","publishedAt":"2023-02-14T16:00:21Z"},{"id":"bTTmJZouBjA","title":"Tumpukan Jenazah Korban Gempa Turki Di Gedung Olahraga","categoryId":"25","channelId":"UCKII0Ml9S5wneKbHswmUrIQ","channelTitle":"CNN Indonesia","tags":["CNN Indonesia","berita terbaru","berita","Indonesia","berita terkini","berita terbaru hari ini","live streaming","top trending","berita hari ini","2022","news","berita politik","news live","breaking news","viral terbaru","live news","youtube news","berita viral","viral","viral hari ini","trending","berita Indonesia","cnn indonesia","kompas tv","inews","net news","tv one","news update","Sekretariat Presiden","Gempa Turkiye","Kota Kahra-Manmaras","Korban Gempa Turkiye"],"thumbnails":"https://i.ytimg.com/vi/bTTmJZouBjA/sddefault.jpg","publishedAt":"2023-02-09T09:33:23Z"},{"id":"6BHX7FrXG44","title":"‘डोभाल पर जाएगा Modi  की कुर्सी’ BJP नेता के दावे से मचा बवाल","categoryId":"25","channelId":"UCuzS3rPQAYqHcLWqOFuY0pw","channelTitle":"News 24","tags":["Latest News","Top News","Today's News","News24","news today","top headlines","news24 live tv","news 24","news 24 live tv","live news","Modi","BJP","Subramanian Swamy"],"thumbnails":"https://i.ytimg.com/vi/6BHX7FrXG44/sddefault.jpg","publishedAt":"2023-02-14T14:31:37Z"},{"id":"TKJneo9BoW4","title":"Uppum Mulakum 2│Flowers│EP# 174","categoryId":"24","channelId":"UCmAPdImtXLGh5E-lTTH4Qmg","channelTitle":"Flowers Comedy","tags":["flowers tv","flower tv comedy","flower tv malayalam","malayalam comedy","malayalam comedy movies","Comedy Utsavam","mimicry","comedy","mimic","stage","kerala","talent","malayalam","entertainment","malayalam cinema","UppumMulakum2","Chakkappazham2"],"thumbnails":"https://i.ytimg.com/vi/TKJneo9BoW4/sddefault.jpg","publishedAt":"2023-02-14T16:00:27Z"},{"id":"EZn6Kyawahs","title":"Valentine 2023 | વેલેન્ટાઈન અમદાવાદીમેન | Amdavadi Man | Gujarati Comedy","categoryId":"24","channelId":"UCK7iCgfQQsBnwuD6w4doHAw","channelTitle":"Amdavadi Man","tags":["Valentine 2023 | વેલેન્ટાઈન અમદાવાદીમેન | Amdavadi Man | Gujarati Comedy","Valentine amdavadiman","Valentine 2023","Valentine special","Gujarati Valentine","Gujju Valentine","Kushal Mistry","Parth parmar","Amdavadi man","Amdavadi man new video","Amdavadi man comedy","Amdavadi man Valentine","Valentine day special"],"thumbnails":"https://i.ytimg.com/vi/EZn6Kyawahs/sddefault.jpg","publishedAt":"2023-02-14T08:17:35Z"},{"id":"6Z7tW64jpTM","title":"DIVINE - Baazigar feat. Armani White | Prod. by Karan Kanchan | Official Music Video","categoryId":"10","channelId":"UCFX8go5jeQ_9_Pk9WFl5tmA","channelTitle":"DIVINE","tags":["divine","divine rapper","divine new song","vivian divine","baazigar","baazigar songs","baazigar divine","baazigar divine reaction","baazigar song","baazigar song divine","armani white","armani white song","armani white baazigar","divine baazigar","gully gang","gully gang song","popular songs","divine armani white","divine armani white baazigar","baazigar new song","alka yagnik","shah rukh khan","hip hop","rap","new song","new songs","new songs 2023","new song 2023","latest song"],"thumbnails":"https://i.ytimg.com/vi/6Z7tW64jpTM/sddefault.jpg","publishedAt":"2023-02-10T05:29:00Z"},{"id":"3l3VlGH0Zes","title":"കരയാതെ  ഒരുപാട് പ്രതീക്ഷകളുമായി പ്രവീണിന്റെ വീട്ടിലേക്ക് സന്തോഷത്തോടെ അയിഷു യാത്രയായി 🥰","categoryId":"22","channelId":"UCZcjeoxG_tu-NvLDH5PTUwg","channelTitle":"T A L K S - LET ME TALK","tags":["#VLLO"],"thumbnails":"https://i.ytimg.com/vi/3l3VlGH0Zes/sddefault.jpg","publishedAt":"2023-02-14T12:36:49Z"},{"id":"fRL9UiVp_nk","title":"Marvel Studios’ Guardians of the Galaxy Vol. 3 | New Trailer | Hindi","categoryId":"1","channelId":"UCah9jr4Ehlrt4Wv-q-CgJkg","channelTitle":"IndiaMarvel","thumbnails":"https://i.ytimg.com/vi/fRL9UiVp_nk/sddefault.jpg","publishedAt":"2023-02-13T06:36:24Z"},{"id":"8Q58gd_Zf2o","title":"Ellyse Perry is Now A Royal Challenger | RCB Shorts","categoryId":"27","channelId":"UCCq1xDJMBRF61kiOgU90_kw","channelTitle":"Royal Challengers Bangalore","thumbnails":"https://i.ytimg.com/vi/8Q58gd_Zf2o/sddefault.jpg","publishedAt":"2023-02-14T17:11:16Z"}]}