{"date":"2023-07-08T10:38:12.332Z","data":[{"id":"QlZNGcVfeF0","title":"Columbia - Quevedo (Video Oficial)","categoryId":"10","channelId":"UCYEmGiiM21tGuCEtDJTfP1w","channelTitle":"Quevedo","publishedAt":"2023-07-06T22:00:11Z"},{"id":"d_6f0JQOfM8","title":"C. Tangana - Oliveira Dos Cen Anos (Video Oficial)","categoryId":"10","channelId":"UCPTQlbt5SZO_SpYvC4Ygl-A","channelTitle":"CTanganaVEVO","tags":["tangana oliveira dos cen anos","oliveira dos cien años","himno celta","c. tangana celta","tangana celta","centenario celta","C. Tangana","Oliveira Dos Cen Anos","Pop","Sony Music Entertainment"],"publishedAt":"2023-07-06T22:00:31Z"},{"id":"NJXZXEhdgI0","title":"PRIMER ENCIERRO de San Fermín 2023 | Toros de La Palmosilla","categoryId":"24","channelId":"UCqlsTzBv49Uiu8Z3IseVgQQ","channelTitle":"RTVE","tags":["encierro","encierro san fermin 2023","san fermin 2023","encierro sanfermines","sanfermines 2023"],"publishedAt":"2023-07-07T06:13:30Z"},{"id":"soA-kbQ2Js4","title":"Bad Gyal, Myke Towers - Mi Lova (Official Video)","categoryId":"10","channelId":"UCOmtuk6Mp66DRFcg81kr3eQ","channelTitle":"BadGyalVEVO","tags":["Bad Gyal","Myke Towers","Mi Lova","mi lova bad gyal","bad gyal mi lova","Bad Gyal Myke Towers","Myke Towers mi lova","mi lova letra","bad gyal chulo","flow 2000 bad gyal","sin carne bad gyal","fiebre","yo soy la que mato bad gyal","flow 2000","mujeres sexualidad entre hombres","zorra","fiebre bad gyal","la prendo bad gyal","beny jr","bobo","alocao","bad gyal fiebre","sin carne","omar montes","sexo","pussy","tremendo cu bad gyal letra","la prendo","bizarrap","quevedo"],"publishedAt":"2023-07-07T00:00:30Z"},{"id":"PPvUnPfErSs","title":"¿Cómo es hacer un VIAJE LARGO en mi Tesla Model S Plaid? - TheGrefg","categoryId":"24","channelId":"UCCEmjNPpJYhGDgaEqeeA4HA","channelTitle":"TheGrefg","tags":["cómo es","hacer","un","viaje largo","tesla","model s","plaid","thegrefg","grefg"],"publishedAt":"2023-07-06T19:47:41Z"},{"id":"9unnI8fnO1M","title":"Jugador rapido que haya ganado el mundial con la letra… con @XoanRamos","categoryId":"17","channelId":"UCh14bht4isvHoO2paCbLE0w","channelTitle":"Davisuuarez2","publishedAt":"2023-07-06T16:20:21Z"},{"id":"yVIH0cHmuuE","title":"JC REYES - PIRIBIRI","categoryId":"10","channelId":"UCca7FqUEssNMZueJT8Jn4KA","channelTitle":"LOS GREEN LANTERS","publishedAt":"2023-07-05T22:00:10Z"},{"id":"CqC3qy23Q5c","title":"👑 AFTER-CHUP KINGS & QUEENS ⚽ NOVEDADES PARA LA FINAL FOUR, SUBIDA DE SUELDOS, POLÉMICAS...","categoryId":"17","channelId":"UCtwslQPB_xJfaFuZv0OETNw","channelTitle":"Kings League ","tags":["games","twitch","kings league","goles kings league","kingsleague","futbol","futbol 7","pique","gerard pique","ibai","ibai llanos","thegrefg","grefg","kun","kun aguero","xbuyer","xbuyer team","buyer","draft kings league","djmario","djmariio","spursito","casillas","iker casillas","analisis kings league","joker","el joker","casillas kings league","kings league jornada","queens league","queens","queen's league","oysho","gemita","paula gonu","violeta","mayichi","espe","morena beltran"],"publishedAt":"2023-07-06T22:04:14Z"},{"id":"rjlYBFoPcJk","title":"HungryBoys funny video😂😂😂|M2DK Best TikTok July 2023 #shorts #TikTok #m2dk #YESorNO","categoryId":"23","channelId":"UCKrIPBpUuS0xFYgL_3LMPGw","channelTitle":"M2DK.マツダ家の日常","tags":["TikTok","Junya1gou","Junya","JunyaLegend","meme","memes","TikTokChallenge","funnyvideo","funnytiktok","mostfunny","JunyaBest","junya1goutiktok","matsudake","M2DK","m2dk","sagawa1gou​","funny","viral","tiktokcompilation","#hungryboys","#CoffinDance​"],"publishedAt":"2023-07-07T14:00:44Z"},{"id":"x5l8Gxh0bzg","title":"👑 Kings League InfoJobs - JORNADA 9 ⚽ #KingsLeagueJ8","categoryId":"17","channelId":"UCtwslQPB_xJfaFuZv0OETNw","channelTitle":"Kings League ","tags":["games","twitch","kings league","goles kings league","kingsleague","futbol","futbol 7","pique","gerard pique","ibai","ibai llanos","thegrefg","grefg","kun","kun aguero","xbuyer","xbuyer team","buyer","draft kings league","djmario","djmariio","spursito","casillas","iker casillas","analisis kings league","joker","el joker","casillas kings league","kings league jornada","queens league","queens","queen's league","oysho","gemita","paula gonu","violeta","mayichi","espe","morena beltran"],"publishedAt":"2023-07-05T20:35:05Z"},{"id":"5M2tSEQsnN4","title":"Kidd Keo - Celine feat Ghost Killer Track -   (Official Video)","categoryId":"10","channelId":"UCBCD1nIuiH-d10_l6Q-8rRg","channelTitle":"Kidd Keo","tags":["Kidd Keo","KiddKeo","Keo","Kidd Keo Dracukeo","Kidd Keo Serpiente Veneno","Kidd Keo 24H","Kidd Keo Lollypop","Kidd Keo Touchdown","Kidd Keo Superstar","Kidd Keo Miss U","Kidd Keo Moon Talk","Igot","Me La Suda","Touchdown","Dracukeo","Aleman","Lil Xan","Trap","Trap en Español","Trap España","Jon Z","BZRP","Duki","Khea","Bad Bunny","Anuel AA","Yung Sarria","C Tangana","Dellafuente","Cruz Cafune","Don Patricio","Rels B","Pimp Flaco","Kinder Malo","Kaydy Cain","Bejo","Yung Beef","Cecilio G"],"publishedAt":"2023-07-06T22:00:05Z"},{"id":"qsQ3QT8it_Y","title":"Esa es solo la piscina de niños! 😡😂 @AmiRodrigueZZ","categoryId":"22","channelId":"UChq_qmwRxTMgmggitRTiIEA","channelTitle":"Amara Que Linda","publishedAt":"2023-07-07T19:11:53Z"},{"id":"kLjJUKINyvo","title":"OT CASTING ZARAGOZA | FASE 2 | OT 2023 (COMPLETO)","categoryId":"24","channelId":"UCc1sAhdaLjfJi11X1awO-yg","channelTitle":"Operación Triunfo Oficial","tags":["ot casting zaragoza","ot zaragoza","fase 2","#otzaragoza","castings ot","casting ot 2023","ot 2023","operación triunfo","noemi galera","audiciones","pase prime","streaming","nueva edición","ciudades","aspirantes","primera fase","canal 24h","canal ot","covers","ot covers","música"],"publishedAt":"2023-07-06T17:13:39Z"},{"id":"Qip3xXCTzh4","title":"MILO J - RINCÓN (Video Oficial)","categoryId":"10","channelId":"UCAPk9W8Ng6epalCoC3YVvsQ","channelTitle":"MILO J","tags":["milo j","miloj","milo","alborde","al borde","reacción milo","ep milo","milagrosa","milagrosa milo j","argentina","trap","trap argentino","rincón","los colores se hacen grises","los colores milo j","rincon milo j","colores milo","colores milo j","baladas"],"publishedAt":"2023-07-06T00:00:08Z"},{"id":"lJrHLnhJl-M","title":"Press This Button = Win $100,000!","categoryId":"20","channelId":"UCIPPMRA040LQr5QPyJEbmXA","channelTitle":"MrBeast Gaming","publishedAt":"2023-07-07T18:30:40Z"},{"id":"ybK-uaF8tLg","title":"Carlos Alcaraz vs Alexandre Muller | Second Round Highlights | Wimbledon 2023","categoryId":"17","channelId":"UCNa8NxMgSm7m4Ii9d4QGk1Q","channelTitle":"Wimbledon","tags":["2023","Grand Slam","Grass","Tennis","Tennis Grandslam","The Championships","Wimbledon","Wimbledon 2023","wimbledon championship","wimbledon tennis","wimbledon video","Always Like Never Before","Match Highlights","Carlos Alcaraz","Carlos","Alcaraz","Carlos Alcaraz 2023","Grand Slam Champion","Spain","Spanish tennis","Wimbledon tradition","Centre Court","SW19","Match highlight","news","tennis news","Carlos Alcaraz vs Alexandre Muller 2023","Carlos Alcaraz vs Alexandre Muller","Alcaraz Highlights","Second Round"],"publishedAt":"2023-07-07T18:00:24Z"},{"id":"p_sf9DFRgBE","title":"Columbia","categoryId":"10","channelId":"UC7PL9aor5qNRhvhWWVXyOqA","channelTitle":"Quevedo - Topic","tags":["Quevedo","Columbia"],"publishedAt":"2023-07-06T22:01:06Z"},{"id":"SKEDuBDm_u0","title":"HARD GZ & KAZE - EL CIELO (Prod. Marcelus Airlinez)","categoryId":"10","channelId":"UCayaN-y6-FJ5tuTcIq6iEyA","channelTitle":"HARD GZ","tags":["EL CIELO","HARD GZ","HARD","GALICIA","HARD GALICIA","Kaze","MARCELUS AIRLINEZ","MARCELUS","RAP","HIP HOP","VERANO 2023","2023"],"publishedAt":"2023-07-06T15:32:16Z"},{"id":"8v3rTn-mMu0","title":"Casillas era RECHAZADO por sus propios compañeros del Real Madrid","categoryId":"24","channelId":"UCXEZrUc8zI1khA7Eri3GAwA","channelTitle":"EmmaHavokOscuro","tags":["iker casillas","casillas","portero","casillas besa a sara carbonero","casillas sufre infarto","iker casillas sufre un infarto","iker casillas atajadas","se retira del futbol","mundial","champions","copa del mundo","iker casillas vs robben","futbol","1999","2000","2002","2006","2008","2010","2014","2015","florentino","real madrid","porto","liga española","españa","parada","top 10","oliver kahn","camiseta","messi","ronaldo","cracks","fifa","espn","chirnguito","arquero","deporte","neuer","keylor navas","ter stegen","buffon","hierro","raul gonzalez","2023"],"publishedAt":"2023-07-07T00:00:04Z"},{"id":"stUofW3whpE","title":"I Buried Treasure in the Bermuda Triangle","categoryId":"24","channelId":"UCX6OQ3DkcsbYNE6H8uQQuVA","channelTitle":"MrBeast","publishedAt":"2023-07-06T17:00:01Z"},{"id":"hbWDxDcktMc","title":"OT CASTING ZARAGOZA | FASE 1 | OT 2023","categoryId":"24","channelId":"UCc1sAhdaLjfJi11X1awO-yg","channelTitle":"Operación Triunfo Oficial","tags":["sigue en directo","castings ot","casting ot 2023","ot 2023","operación triunfo","castings en directo","noemi galera","audiciones","pase prime","streaming","nueva edición","ciudades","aspirantes","primera fase","canal 24h","canal ot","covers","ot covers","música","casting completo","#otzaragoza","ot zaragoza","zaragoza","ot casting zaragoza"],"publishedAt":"2023-07-06T12:28:01Z"},{"id":"C0EYKxF1oTI","title":"TXT (투모로우바이투게더), Jonas Brothers 'Do It Like That' Official MV","categoryId":"10","channelId":"UC3IZKseVpdzPSBaWxBxundA","channelTitle":"HYBE LABELS","tags":["HYBE","HYBE LABELS","하이브","하이브레이블즈"],"publishedAt":"2023-07-07T04:00:03Z"},{"id":"FS__SaIBf-A","title":"Beéle, Farruko - Santorini (Official Video)","categoryId":"10","channelId":"UCYQV_J85c0cjxixuXIoEnzw","channelTitle":"BeeleVEVO","tags":["Beéle","Beele","Hear This Music","beele loco","natti natasha","musica latina","nueva musica beele","mi carta","beele video oficial","guaro","beele 2023","loco","si te interesa","barranquilla bajo cero","lo nuevo de beele","dancehall","regueton","video nuevo de beele","SANTORINI","presave","reserva","afterparty","FARRUKO","cuando no estas yo te pienso te pienso","cuando no estas yo","no me gusta lo mucho que esto me está gustando","5020 Records","Beéle Farruko","Latin"],"publishedAt":"2023-07-07T00:00:07Z"},{"id":"-FQapMK_Kvw","title":"Myke Towers - LALA (Lyrics/Letra)","categoryId":"10","channelId":"UCHuDwbloOT6cmozpGbWnjBQ","channelTitle":"Arcade Music","tags":["myke towers","lala","myke towers lala","lala lyrics","lala letra","lala myke towers","myke towers lala lyrics","myke towers lala letra","lala letra myke towers","lala lyrics myke towers","Myke Towers - LALA (Lyrics)","Myke Towers - LALA (Letra)","myke towers new song","myke towers latest","myke towers song","latin songs","latin pop","pop","myke towers lala song"],"publishedAt":"2023-07-06T16:00:00Z"},{"id":"ArmDp-zijuc","title":"NewJeans (뉴진스) 'Super Shy' Official MV","categoryId":"10","channelId":"UC3IZKseVpdzPSBaWxBxundA","channelTitle":"HYBE LABELS","tags":["HYBE","HYBE LABELS","하이브","하이브레이블즈"],"publishedAt":"2023-07-07T03:58:10Z"},{"id":"e-bEtdqvsJE","title":"Jaimito reaccionando a videos #60","categoryId":"20","channelId":"UCrZieFQanxjzoZzqAa0tQFg","channelTitle":"CrisPierri","publishedAt":"2023-06-29T22:30:04Z"},{"id":"098ogxH5pZ0","title":"RESUMEN | España 5-1 Ucrania | Semifinal Euro sub-21| 🔴 SEFUTBOL","categoryId":"17","channelId":"UCJ2F8qpzHRk3RdJZ4YXLbxQ","channelTitle":"Selección Española de Fútbol (SeFutbol)","tags":["sefutbol","Seleccion Española de Futbol","Spain National Football Team","España","La Roja","Futbol Español","Fútbol","Selección Española","Roja","España entrenamiento","Selección española","Vamos España","Spain","Spanish national team","Entrenamiento","goles","golazos","españa","UEFA","Suiza","U21Euro","#U21Euro","UEFA U21 Euro","Bucarest","Giulesti Stadium","Sergio Gómez","Santi Denia","cuartos de final","semifinales","Juan Miranda"],"publishedAt":"2023-07-06T01:36:45Z"},{"id":"2ZnmlTyxOVs","title":"SIDHU MOOSE WALA, DIVINE - Chorni | Official Audio","categoryId":"10","channelId":"UCFX8go5jeQ_9_Pk9WFl5tmA","channelTitle":"DIVINE","publishedAt":"2023-07-07T11:29:56Z"},{"id":"xuiIPXvxDhs","title":"Lo siento mucho.","categoryId":"24","channelId":"UCnmlCrWnJZ-YdDFcVKOnjhA","channelTitle":"Ampeterby7","tags":["ampeter","ampeterby7","Lo siento mucho.","lo","siento","mucho","siento mucho","lo siento","la velada","la velada 3","ampeter vs abraham"],"publishedAt":"2023-07-06T18:51:09Z"},{"id":"Boe6H08ZlCM","title":"Así es el Día Más Importante de Estados Unidos | Clavero","categoryId":"24","channelId":"UCSG0wVzhyjp3xdpY6CfelbA","channelTitle":"HiClavero","tags":["HiClavero","hiclaveroo","clavero","claveroo","Vlog","Así","es","el","día","más","importante","de","Estados Unidos","Los Angeles","4 de Julio","Estados","independencia","julio","verano","comida","hot dogs","fuegos artificiales","clavero y polina","polina","clavero novia","bycraftxx","California","EEUU","USA"],"publishedAt":"2023-07-06T15:00:00Z"},{"id":"Ysg57_DBNoY","title":"¡TODO se ESTIRARÁ después de VER ESTE VIDEO! 😱","categoryId":"24","channelId":"UCnm1ctk8ujjQlenfI0trHWw","channelTitle":"Mikecrack Fans","tags":["mikecrack","mike","Mikecrack Fans","Fans de Mikecrack","Mikecrack Fan Club","Mikecrack Club","mikecrak","mike crack"],"publishedAt":"2023-07-06T17:00:20Z"},{"id":"igIfiqqVHtA","title":"Taylor Swift - Enchanted (Taylor's Version) (Lyric Video)","categoryId":"10","channelId":"UCANLZYMidaCbLQFWXBC95Jg","channelTitle":"TaylorSwiftVEVO","tags":["taylor swift","taylor","swift","speak now taylors version","taylor’s version","speak now TV","speak now taylor’s version","speak now from the vault","speak now vault songs","speak now recrecording","new taylor swift","taylor swift album","taylor swift speak now","taylor speak now"],"publishedAt":"2023-07-07T04:00:21Z"},{"id":"pMNTaMHVEMY","title":"Celular - Nicky Jam x The Chainsmokers x Maluma | Video Oficial","categoryId":"10","channelId":"UCpb_iJuhFe8V6rQdbNqfAlQ","channelTitle":"NickyJamTV","tags":["Nicky Jam","NickyJamPR","nicky","reggaeton","latin","curiosidad","urbano","el amante","equis","travesuras","piensas en mi","bad bunny","jbalvin","fan de tus fotos","musica nueva 2023","reggaeton nuevo","reggaeton 2023","karol g","nicky jam","2023","niki yan","te bote","ojos rojos","novia","porfa","bizarrap","toy a mil","flowers","Miley Cyrus","equiz","ferxxo","normal","pantysito","prohibidox","feid","fercho","peso pluma","yailin","6ix9ine","The Chainsmokers","maluma","coco loco","Don't Let Me Down","closer","takeway","roses","paris","celular","cellular"],"publishedAt":"2023-07-07T00:00:12Z"},{"id":"5DBPgBtfMLA","title":"이모티콘 순서대로 먹기","categoryId":"22","channelId":"UCPhHBEtG6dVZ5fJKoNArcJw","channelTitle":"승비니 Seungbini","publishedAt":"2023-07-06T09:55:00Z"},{"id":"fx6IUajgLSs","title":"Palabras de la Princesa de Asturias y de Girona en los Premios Fundación Princesa de Girona 2023","categoryId":"25","channelId":"UC7DIwkg2oz6N7_ZVzUG3prA","channelTitle":"casarealtv","tags":["casa real","monarquía","zarzuela","rey Felipe","Jefatura","Letizia","príncipe felipe","felipe VI","king","queen","jefatura del estado","felipe","familia real","Rey","Felipe","Reina","Princesa","Asturias","Girona","Leonor","Infanta","Sofía"],"publishedAt":"2023-07-05T20:22:32Z"},{"id":"tvfxxgcY1X8","title":"Sin Arroz No Hay Japón | La Capital","categoryId":"26","channelId":"UCEwl20VxZ3AwOgiKMZtI1GQ","channelTitle":"La Capital","tags":["comida japonesa","la capital","viajar japon","arroz japon","sushi japones","izakaya","sake japon","carne caballo","comida en japon","salsa soya"],"publishedAt":"2023-07-06T21:00:27Z"},{"id":"8ytj4UZH4RA","title":"Let’s get Super Shy! 🫣#ImSuperShy #NewJeans #뉴진스 #NewJeans_SuperShy #Time_to_NewJeans","categoryId":"10","channelId":"UCMki_UkHb4qSc0qyEcOHHJw","channelTitle":"NewJeans","publishedAt":"2023-07-07T06:00:02Z"},{"id":"Sg7Cq5nhYeI","title":"BASURA + IMPRESORA 3D  = 💎💡","categoryId":"24","channelId":"UC76hs2bdrebFYvdR-I8bwyw","channelTitle":"vicesat","tags":["bicicleta electrica","ebike","top","gadgets","electric bike","electric motorcycle","diy","best","homemade","patinete electrico","moto electrica","motos","motorcycle","lego","lego bike","lego car","impresora 3d","imprimir 3d","como imprimir en 3d","impresora 3d casera","impresora 3d barata","3d printer","best 3d printer","mejor impresora 3d","impresora 3d filamento","funcionamiento impresoras 3d","como funciona una impresora 3d","review","impresion 3d","trucos","imprimir 3d coche","piezas coche"],"publishedAt":"2023-07-05T19:00:10Z"},{"id":"Sg9hqLNyASU","title":"La monja II | Tráiler oficial","categoryId":"1","channelId":"UCm8qFuubCgKlxdgMt_2WZBQ","channelTitle":"Warner Bros. Pictures España","tags":["Anna Popplewell","Annabelle","Coming Soon","Conjuring","Conjuring Universe","Gary Dauberman LaMonja","Horror","Ian Goldberg","James Wan","Jonas Bloquet","LaMonjaII","Michael Chaves","Movie","Nun","Nun 2","Richard Naing","Storm Reid","Taissa Famiga","The Conjuring","The Nun","The Nun 2","Trailer 2023"],"publishedAt":"2023-07-06T16:00:21Z"},{"id":"Are-lMlKcGs","title":"4-year-old has 'severe case of the Mondays' #shorts","categoryId":"25","channelId":"UCXwRxm0zS0jBNTMOVI6xZJw","channelTitle":"KHOU 11","tags":["houston","khou","khou11","news"],"publishedAt":"2023-06-26T14:25:30Z"},{"id":"FtbMX_aQlFo","title":"Arda Güler Welcome to Real Madrid","categoryId":"17","channelId":"UCexoonWpGA1nwQctHsDv7ZQ","channelTitle":"MadridistaTV","tags":["real madrid","sergio ramos","courtois","ronaldo","varane","modric","kroos","casemiro","benzema","vinicius","rodrygo","luka jovic","isco","james rodriguez","goals","assists","futbol","football","futebol","fußball","soccer"],"publishedAt":"2023-07-06T08:23:20Z"},{"id":"TFfraRUmGvA","title":"PAPI GAVI REACCIONA \"COLUMBIA\" DE QUEVEDO","categoryId":"10","channelId":"UC4dzzNaiHmXNaeJK9W-Dsyg","channelTitle":"Walter Alejandro","tags":["papi","gavi","reacciona","columbia","de","quevedo","papi gavi","papi gavi quevedo","walter","alejandro","walter alejandro","walter alejandro quevedo","reaccion","reaccion quevedo","reaccion columbia","quevedo columbia","papi gavi columbia"],"publishedAt":"2023-07-07T12:51:28Z"},{"id":"NxrgwJMq4Yc","title":"Que son estas cajas que les ponen a los tanques? 🤔","categoryId":"24","channelId":"UCnusCHicJfhJ1huoCWfYH_A","channelTitle":"Homosapiens","publishedAt":"2023-07-06T23:29:00Z"},{"id":"tD5LdvmUuAs","title":"Sara Socas, SFDK - Siente","categoryId":"10","channelId":"UC9SQmIV59RjSc96m9nAozQw","channelTitle":"Sara Socas","tags":["sara socas","sara socas feminista","ahora me quiero mas sara socas","sara socas ahora me quiero mas","rap feminista","rap en español","sara socas rapder","sara socas sfdk","sfdk","zatu","sara socas cancion","sara secas","sara rocas"],"publishedAt":"2023-07-06T21:59:00Z"},{"id":"HvTnvhvDGBI","title":"OT CASTING BARCELONA | FASE 2 | OT 2023 (COMPLETO)","categoryId":"24","channelId":"UCc1sAhdaLjfJi11X1awO-yg","channelTitle":"Operación Triunfo Oficial","tags":["sigue en directo","ot casting barcelona","castings ot","casting ot 2023","ot barcelona","fase 2","ot 2023","operación triunfo","castings en directo","#otbarcelona","noemi galera","audiciones","pase prime","streaming","nueva edición","ciudades","aspirantes","primera fase","canal 24h","canal ot","covers","ot covers","música"],"publishedAt":"2023-07-04T19:05:35Z"},{"id":"9iUcUMqVlUk","title":"Los jugadores del RC Celta reaccionan al himno del Centenario por C. Tangana 💙💯","categoryId":"17","channelId":"UCCJLVZYqRb_85b2Flpg04cg","channelTitle":"RC Celta","tags":["celta de vigo","celta","rc celta","celta media","celta vigo","rccelta","celta tv","celtamedia","RC Celta","Iago Aspas","Kevin Vázquez","Fran Beltrán","Franco Cervi","Himno del Centenario","C. Tangana","Reacción de jugadores","Centenario del RC Celta","Música","Entrevistas","Vídeo reacción","Himno oficial","Composición musical","Evento especial","Himno deportivo","Historia del club","Himno único","Vídeo viral","Aniversario del club","LaLiga","LaLiga EA Sports","Himno del Celta","Himno C Tangana","C Tangana"],"publishedAt":"2023-07-06T10:20:13Z"},{"id":"fpjGG3O3bas","title":"POSTRE DE VERANO, DE LIMÓN 🤩, SIN HORNO Y SIN LECHE CONDENSADA - Loli Domínguez. Recetas - Tutorial","categoryId":"26","channelId":"UC5ONfXPjWgqElh0NZaRJ1tg","channelTitle":"La Cocina de Loli Dominguez","tags":["Loli Domínguez","La Cocina de Loli Domínguez","cocina","Postre de verano","postre de verano receta","postre de verano gourmet","postre de verano para niños","postre de verano sin horno","postre de verano receta original","postre de verano recetas","postre de verano receta casera","postre de verano receta fácil","receta postre de verano","postres de verano fáciles y rápidos","cómo preparar postre de verano","postres","tartas de verano","tartas de verano sin horno","tartas de verano frías","Tartas"],"publishedAt":"2023-07-06T13:50:12Z"},{"id":"st6-0--2D0c","title":"Greeicy, Danny Ocean - ZHA (Yeliana - Capítulo 3) (Official Video)","categoryId":"10","channelId":"UCf-Szc6YLd8rMnMXGThznFg","channelTitle":"GreeicyVEVO","tags":["Greeicy","Danny Ocean","ZHA","greeicy danny ocean ZHA","zha","zha letra greeicy","yeliana que me quiera","greeicy lokita","greeicy letra lokita","greeicy nueva cancion","danny ocean fuera del mercado","me rehuso","el dembow","greeicy rendon","greeicy la carta","album la carta greeicy","greeicy andres cepeda","greeicy feid","greeicy los besos","greeicy destino","amantes greeicy","greeicy mike bahia","mike bahia greeicy","greeicy chica vampiro","greeicy"],"publishedAt":"2023-07-07T00:00:07Z"},{"id":"cK3O8UHHzZ4","title":"Ana Torroja, desenmascarada como Ratita | Mask Singer: Adivina quién canta","categoryId":"24","channelId":"UC84t25xqhPEPpGY7NBZJ_eA","channelTitle":"Antena 3","tags":["Antena 3","antena3.com","Vídeos","Clips","Video","Mask Singer","Adivina quien canta","Javier Calvo","Javier Ambrosi","Ana Obregon","Monica Naranjo","Arturo Valls","Alaska","Hada","Olvido"],"publishedAt":"2023-07-05T23:13:55Z"},{"id":"73At5q-n-N0","title":"Cuánto debería GANAR para ser CLASE ALTA?! 🔺 #Shorts","categoryId":"27","channelId":"UClVxNS4V4yanN64iyU8pKmQ","channelTitle":"BaiJavier","publishedAt":"2023-07-06T15:00:04Z"}]}