{"date":"2023-04-29T16:45:18.803Z","data":[{"id":"7L7bfcwomNg","title":"Overloading the Game So Hard It Takes 2.5 Hours to Load - Hydroneer","categoryId":"20","channelId":"UCto7D1L-MiRoOziCXK9uT5Q","channelTitle":"Let's Game It Out","tags":["let's game it out","lets game it out","let game it out","let'sgameitout","letsgameitout","letgameitout","game it out","gameitout","lgio","josh let's game it out","let's game it out josh","lgio josh","josh lgio","let's game it out simulator","josh simulator","funny moments","big ambitions","let's game it out startup company","big ambitions full game","funny games","hydroneer","hydroneer game","hydroneer gameplay","hydroneer let's game it out","let's game it out hydroneer","lgio hydroneer","josh hydroneer"],"publishedAt":"2023-04-28T15:00:05Z"},{"id":"itnqEauWQZM","title":"Transformers: Rise of the Beasts | Official Trailer (2023 Movie)","categoryId":"1","channelId":"UCF9imwPMSGz4Vq1NiTWCC7g","channelTitle":"Paramount Pictures","tags":["transformers rise of the beasts trailer","transformers rise of the beasts","new transformers trailer","anthony ramos","dominique fishback","steven caple jr","ron perlman","pete davidson","peter dinklage","michelle yeoh","michael bay","peter cullen","Tobe Nwigwe","John DiMaggio","David Sobolov","Michaela Jae Rodriguez","Cristo Fernandez","Tongayi Chirisa","Colman Domingo"],"publishedAt":"2023-04-27T13:00:05Z"},{"id":"VxzpifmEEes","title":"SIDEMEN AMONG US BUT THE IMPOSTER HAS SUPER SPEED","categoryId":"22","channelId":"UCh5mLn90vUaB1PbRRx_AiaA","channelTitle":"MoreSidemen","tags":["sidemen","moresidemen","miniminter","ksi","zerkaa","behzinga","tbjzl","vikkstar","wroetoshaw"],"publishedAt":"2023-04-27T17:00:13Z"},{"id":"aWKtAqIUEl4","title":"IShowSpeed & Kai Cenat - Dogs (Official Music Video)","categoryId":"20","channelId":"UCWsDFcIhY2DBi3GB5uykGXA","channelTitle":"IShowSpeed","tags":["ishowspeed"],"publishedAt":"2023-04-27T19:00:07Z"},{"id":"UOaMesN5vrY","title":"Baby Girl","categoryId":"24","channelId":"UCDo9msNItILnyF_Y2eHaNQg","channelTitle":"RiceGum","tags":["pregnant mom baby shower pregnancy daughter son"],"publishedAt":"2023-04-27T18:23:57Z"},{"id":"cC1afXxfIDc","title":"My First Game Of AFL 23 (Gameplay)","categoryId":"20","channelId":"UCeM4ombBmANIkEM2RTgpd5Q","channelTitle":"Caden MacDonald","tags":["AFL","AFL 23","AFL 23 Gameplay","AFL23","AFL Evolution","AFL Evolution 2","AFL 23 Career Mode","AFL 23 First Game","Big Ant","Big Ant Studios","Australian Football League"],"publishedAt":"2023-04-28T06:30:08Z"},{"id":"nCRSwgr7pNw","title":"Rebuilding A Flooded $2,000,000 McLaren P1 | Part 2","categoryId":"2","channelId":"UCvAhDxNNUDhi78tMXVGBUaQ","channelTitle":"Tavarish","tags":["aston martin","mercedes","amg","hyundai","bmw","lamborghini","ferrari","toyota","supra","mr2","sw20","3sgte","2jz","1jz","sl55","r230","r231","m113k","vantage","v8","v12","v10","v6","gallardo","turbo","cheap","budget","diy","wrench everyday","doug demuro","chrisfix","hoovies garage","tavarish","jalopnik","mightycarmods","motor trend","roadkill","hack","bendpak","tools","lift","4 post","2 post","quick jack","welding","how to","tutorial","mclaren","p1","675","hypercar","bugatti","chiron","flood","wrecked","copart","hurricane","ian","top gear","restoration","goonzquad","matarmstrong"],"publishedAt":"2023-04-27T22:00:39Z"},{"id":"AeEYQ62t8hA","title":"The Final Episode - FULL - The Late Late Show with James Corden","categoryId":"24","channelId":"UCJ0uqCI0Vqr2Rrt1HseGirg","channelTitle":"The Late Late Show with James Corden","tags":["James Corden","The Late Late Show","Colbert","late night","late night show","Stephen Colbert","Comedy","monologue","comedian","impressions","celebrities","carpool","karaoke","CBS","Late Late Show","Corden","joke","jokes","funny","funny video","funny videos","humor","celebrity","celeb","hollywood","famous"],"publishedAt":"2023-04-28T08:35:00Z"},{"id":"nV8UZJNBY6Y","title":"Adele - The Final Carpool Karaoke","categoryId":"24","channelId":"UCJ0uqCI0Vqr2Rrt1HseGirg","channelTitle":"The Late Late Show with James Corden","tags":["The Late Late Show","Late Late Show","James Corden","Corden","late night","late night show","comedy","comedian","celebrity","celeb","celebrities","CBS","joke","jokes","funny","funny videos","funny video","humor","hollywood","famous","adele","adele carpool","i drink wine","last carpool karaoke","james corden adele"],"publishedAt":"2023-04-24T16:00:26Z"},{"id":"f9BwB3SBPOg","title":"The Hunger Games: The Ballad of Songbirds & Snakes (2023) Official Trailer","categoryId":"1","channelId":"UCjvqqA-Eogozfm244OhUESw","channelTitle":"The Hunger Games","tags":["The Hunger Games: The Ballad of Songbirds and Snakes","The Hunger Games","Hunger Games","The Ballad of Songbirds and Snakes","Ballad of Songbirds and Snakes","Official trailer","The Ballad of Songbirds and Snakes official trailer","the hunger games official trailer","hunger games trailer","Tom Blyth","Rachel Zegler","Coriolanus Snow","post-war capitol","Lucy Gray Baird","District 12","Panem","Susan Collins","adaptation"],"publishedAt":"2023-04-27T22:00:02Z"},{"id":"8pccDb9QEIs","title":"I absolutely cannot recommend Star Wars Jedi: Survivor (PC Review)","categoryId":"20","channelId":"UCZ7AeeVbyslLM_8-nVy2B8Q","channelTitle":"Skill Up","tags":["skill up","skill","up","gameplay","games","guide","Star Wars Jedi: Survivor Review","jedi survivor","jedi survivor review","star wars jedi survivor","review","game review","star wars jedi survivor gameplay","star wars jedi fallen order","cal kestis","cal kestis poncho","video review","star wars jedi survivor walkthrough","jedi","koboh","open world games","game reviews","lightsaber","lightsaber duel","story mode","bd1","jedi survivor gameplay","jedi survivor cutscenes","jedi survivor part 1","ps5","xbox","pc","4k"],"publishedAt":"2023-04-28T13:00:14Z"},{"id":"vX3-MLNLASg","title":"Can You Farm 1,000,000 Cookies in 100 Minecraft Days?","categoryId":"20","channelId":"UCIVSqoHCUN1XdEpiVItxfoQ","channelTitle":"aCookieGod","tags":["acookiegod","a cookie god","a cookie god minecraft","cookie minecraft","minecraft cookie","minecraft cookie god","cookie god","acookiegod series","acookiegod hardcore","minecraft hardcore","hardcore minecraft","minecraft","extracookie","100 days","acookiegod 100 days","i crafted 1000000 cookies in minecraft hardcore","how many cookies can you craft in 100 days?","can you farm 1000000 cookies in 100 minecraft days?","i survived 100 days farming 1000000 cookies in minecraft hardcore"],"publishedAt":"2023-04-26T12:00:43Z"},{"id":"gSDtNkKPiDg","title":"The WEIGHTLESS Machine","categoryId":"24","channelId":"UCp68_FLety0O-n9QU6phsgw","channelTitle":"colinfurze","publishedAt":"2023-04-27T15:00:34Z"},{"id":"6emgiatRGu4","title":"Stray Kids \"★★★★★ (5-STAR)\" Trailer","categoryId":"10","channelId":"UCaO6TYtlC8U5ttz62hTrZgg","channelTitle":"JYP Entertainment","tags":["JYP Entertainment","Stray Kids","스트레이 키즈","SKZ","스키즈","방찬","BANG CHAN","리노","LEE KNOW","창빈","서창빈","CHANGBIN","SEOCHANGBIN","현진","황현진","HYUNJIN","HWANGHYUNJIN","한","한지성","HAN","HANJISUNG","필릭스","FELIX","승민","김승민","SEUNGMIN","KIMSEUNGMIN","아이엔","양정인","I.N","YANGJEONGIN","stray kids comeback","스트레이 키즈 컴백","스키즈 컴백","skz comeback","스트레이키즈 트레일러","스키즈 트레일러","stray kids trailer","Stray Kids teaser","스트레이 키즈 티저","skz","5-STAR","★★★★★","스트레이 키즈 5STAR","스키즈 5STAR","Stray Kids 5STAR","5STAR","SKZ 5STAR","5STAR 트레일러","스키즈 별","stray kids star","skz star","스트레이키즈 별"],"publishedAt":"2023-04-27T14:59:59Z"},{"id":"G3fiwwK9SM8","title":"Have Arsenal “bottled it” will Man City be Champions? | Fan Debate Part 2","categoryId":"17","channelId":"UCjXIw1GlwaY1IzpW_jN9iCQ","channelTitle":"The Overlap","tags":["Sky Sports","Sport","Football","Premier League","Champions League","Gary Neville","MNF","Monday Night Football","Jamie Carragher","the overlap","overlap","g nev","nev","interview","Arsenal","Man City","Manchester City","Haaland","Saka","Martinelli","Kevin De Bruyne","Arteta","Guardiola","Man City v Arsenal Highlights","Premier League Highlights","Fan Debate","Arsenal bottled it","Holding","Ben White","Gabriel Jesus","Zinchenko","AFTV","Robbie AFTV","Esteemed Kompany","Pippa Monquie","Steven Mcinerney","Tactics"],"publishedAt":"2023-04-28T19:17:14Z"},{"id":"u3DCW-Ai6b4","title":"HIGHLIGHTS: Manchester City v Arsenal | Premier League","categoryId":"17","channelId":"UC0jPwNs4B7yJySNewHan5hQ","channelTitle":"Optus Sport","tags":["how to watch","optus sport","australia","highlights","premier","league","goal","premier league highlights","goals","soccer","football","premier league","epl","premier league fixtures","uefa","fifa","fa","pl","epl highlights","laliga","la liga","spanish league","arsenal","southampton","epic","draw","crystal","palace","everton","liverpool","leeds","leicester","man","city","manchester","haaland","de bruyne","holding","arteta","guardiola","pep"],"publishedAt":"2023-04-26T21:55:18Z"},{"id":"HYIb5IzvM4k","title":"The Kardashians | Season 3 Official Trailer | Hulu","categoryId":"24","channelId":"UCE5mQnNl8Q4H2qcv4ikaXeA","channelTitle":"Hulu","tags":["hulu","disney","hulu movies","hulu shows","Disney+","new series","The Kardashians","Kris","Kourtney","Kim","Khloé","Kylie","motherhood","family","hulu originals","disney+","hulu disney","The Kardashians show hulu","The Kardashians hulu","The Kardashians Season 3 hulu","The Kardashians Season 3 episodes","The Kardashians Season 3 hulu series","Kardashians Season 3","Kardashians Season 3 trailer","The Kardashians trailer","The Kardashians season 3","kim kardashian","kylie jenner","kourtney kardashian"],"publishedAt":"2023-04-27T17:12:46Z"},{"id":"r51cYVZWKdY","title":"The Flash - Official Trailer 2","categoryId":"1","channelId":"UCiifkYAs_bq1pt_zbNAzYGg","channelTitle":"DC","tags":["Andy Muschietti","Barry Allen","Batman","Ben Affleck","Bruce Wayne","Coming Soon","DC","DC Comics","DC Extended Universe","Ezra Miller","Film","Film Trailer","Film Warner","General Zod","Iris West","Kiersey Clemons","Michael Keaton","Michael Shannon","Movie","Multiverse","Official Trailer","Super Hero","Superhero","The Batman","The Flash","Trailer","Trailer 2023","WB","Warner","Warner Bros","Warner Brothers"],"publishedAt":"2023-04-25T19:00:18Z"},{"id":"NFnAuiklEug","title":"TAEYANG - ‘Shoong! (feat. LISA of BLACKPINK)’ PERFORMANCE VIDEO","categoryId":"10","channelId":"UCg8ZzloDPTrOiGztK0C9txQ","channelTitle":"THEBLACKLABEL","tags":["YG Entertainment","YG","와이지","K-pop","BIGBANG","빅뱅","TAEYANG","태양","동영배","白夜","WHITE NIGHT","TBL","THEBLACKLABEL","SOL","PRAYER","SOLARL","VIBE","바이브","지민","Jimin","JIMIN","BTS","방탄소년단","박지민","봄여름가을겨울","달링","눈코입","DARLING","WAKE ME UP","새벽 1시","1AM","RINGA LINGA","링가 링가","나만 바라봐","ONLY LOOK AT ME","I'LL BE THERE","웨딩드레스","I NEED A GIRL","WHERE U AT","comback","KPOP","K-POP","POP","더블랙레이블","TEHBLACKLABEL","theblacklabel","blackpink","yg entertainment","LISA","리사","sm entertainment","jyp entertainment","bts","big hit entertainment","나의마음에","seed","DowntoEarth","M/V","EP","나의 마음에"],"publishedAt":"2023-04-25T09:01:51Z"},{"id":"MIh2EueRmk0","title":"Boogie Woogie Queen Gets A Police Escort To The Piano","categoryId":"10","channelId":"UClw8Huc_XZcz46GJh5Z0wuA","channelTitle":"Brendan Kavanagh","publishedAt":"2023-04-27T15:14:51Z"},{"id":"Sz1swnk0dgA","title":"Star Wars Jedi: Survivor - Jedi Coaching Sessions Trailer","categoryId":"20","channelId":"UCOsVSkmXD1tc6uiJ2hc0wYQ","channelTitle":"EA Star Wars","tags":["star wars","jedi survivor","star wars jedi survivor","jedi survivor trailer","star wars jedi survivor trailer","star wars survivor","Cameron Monaghan","Mark Hamill","Star Wars Trailer","SW","Survivor","JS","Jedi Fallen Order","SWJFO","JFO","Jedi Fallen Order 2","JFO 2","Cal Kestis","BD-1","Lightsaber","EA","EA Star Wars","EASW","Respawn","Respawn Star Wars","Cere Junda","Bode Akuna","Gameplay","Story Trailer","Merrin","Greez","Greez Dritus","Gen’Dai","Rayvis"],"publishedAt":"2023-04-27T15:59:22Z"},{"id":"PXE9EntPZ8I","title":"These New South Whales cover Chumbawamba 'Tubthumping' for Like A Version","categoryId":"24","channelId":"UCd2KNtfphz8HvYzM4pwtHmg","channelTitle":"triple j","tags":["these new south whales","these new south whales like a version","chumbawamba tubthumper","chumbawamba tubthumping","tubthumping cover","these new south whales interview","these new south whales changes","aaron gocs","hatchie","dz deathrays"],"publishedAt":"2023-04-27T23:33:16Z"},{"id":"Q07Og0afEnM","title":"BETA SQUAD SLIP N SLIDE FOOTBALL CHALLENGE","categoryId":"24","channelId":"UCDMHyBFbyJIKFiEwHty-u5Q","channelTitle":"Aj Shabeel","tags":["beta squad","slip","and","slide","football","challenge","slip and slide","slip n slide","giant slip n slide","largest slip n slide","biggest slip n slide","slip n slide football","beta squad slip n slide","slip n slide challenge","slippery football challenge","niko omilana","sharky","chunkz","kingkennytv","aj shabeel","worlds biggest slip n slide","slippery football","worlds largest slip n slide football","football slip n slide","beta squad slip n slide football"],"publishedAt":"2023-04-28T17:00:02Z"},{"id":"cYb_HFHJJHs","title":"Twisted Metal | Official Teaser | Peacock Original","categoryId":"24","channelId":"UCPgMAS8woHJ_o_OZdTR7kcQ","channelTitle":"Peacock","tags":["peacock","peacock tv","peacock streaming service","peacock original","peacock streaming","peacock tv streaming","streaming on peacock 2023","streaming on peacock new","peacock new trailers","peacock tv shows","streaming on peacock","peacock app","twisted metal","twisted metal show","twisted metal trailer","twisted metal teaser","twisted metal peacock","twisted metal tv series","twisted metal sweet tooth","anthony mackie","anthony mackie twisted metal","peacock twisted metal trailer"],"publishedAt":"2023-04-28T15:30:15Z"},{"id":"KllDnkP1f48","title":"Arrow Vs. GIANT Balloons Racing!","categoryId":"17","channelId":"UC5f5IV0Bf79YLp_p9nfInRA","channelTitle":"How Ridiculous","tags":["how ridiculous","rexy","44club"],"publishedAt":"2023-04-27T21:00:15Z"},{"id":"dd1OSFYzE9s","title":"Machine Gun Kelly X Cordae - Doja Freestyle","categoryId":"10","channelId":"UCUs8sGiP4avNaYNVO22INhQ","channelTitle":"Machine Gun Kelly","tags":["machine gun kelly","cordae","freestyle","doja","the cypher","kells","MGK","Colson","MGK and Cordae","Kellyvision","freestyle MGK","freestyle cordae","Machine Gun Kelly 2023","new mgk","new cordae"],"publishedAt":"2023-04-26T16:00:10Z"},{"id":"-GQg25oP0S4","title":"SEVENTEEN (세븐틴) '손오공' Official MV","categoryId":"10","channelId":"UC3IZKseVpdzPSBaWxBxundA","channelTitle":"HYBE LABELS","tags":["HYBE","HYBE LABELS","하이브","하이브레이블즈"],"publishedAt":"2023-04-24T08:58:11Z"},{"id":"M-WKprPrjHw","title":"This yellow is toxic   | How To Cook That Ann Reardon","categoryId":"24","channelId":"UCsP7Bpw36J666Fct5M8u-ZA","channelTitle":"How To Cook That","tags":["Food colours","are food colours safe?","FDA","current research","how to cook that","ann reardon","food scientist","dietitian","food color","food dye"],"publishedAt":"2023-04-28T09:30:15Z"},{"id":"ctlz0R1tSZE","title":"Disney's Wish | Official Teaser Trailer","categoryId":"1","channelId":"UC_976xMxPgzIa290Hqtk-9g","channelTitle":"Walt Disney Animation Studios","tags":["Disney","Walt Disney Animation Studios","Disney Animation","Walt Disney","Animation"],"publishedAt":"2023-04-27T12:41:06Z"},{"id":"tiOrbqx62O4","title":"this game is for KIDS!? [Amanda The Adventurer]","categoryId":"20","channelId":"UCiYcA0gJzg855iSKMrX3oHg","channelTitle":"CoryxKenshin","tags":["amanda the adventurer","amanda","the","adventurer","gameplay","game","full","new","full game","part 1","ending","bad","playthrough","walkthrough","how to","scary","horror","jumpscare","wooly","coryxkenshin","cory","kenshin","funny","hilarious","moments","reaction","edits"],"publishedAt":"2023-04-26T17:20:33Z"},{"id":"DKrelwjugQA","title":"Calm Down","categoryId":"10","channelId":"UCy6qn2oxmoXA4_gBA5Q7zPw","channelTitle":"Rema - Topic","tags":["Rema","Ｒｅｍａ","Selena Gomez","セレーナゴメス","セレーナ・ゴメス","Rave & Roses Ultra","Calm Down"],"publishedAt":"2023-04-27T22:59:00Z"},{"id":"38dIHkJMtHw","title":"Super - SEVENTEEN [Music Bank] | KBS WORLD TV 230428","categoryId":"10","channelId":"UC5BMQOsAB8hKUyHu9KI6yig","channelTitle":"KBS WORLD TV","tags":["yt:cc=on","kbs","kbsworld","kbs world","KBSWorld","KBS","kbsworldTV","kbs월드","월드TV","kbs 월드","world tv","KBS WORLD TV","손오공","가요","가수","음악","케이팝","세븐틴","SEVENTEEN"],"publishedAt":"2023-04-28T09:24:56Z"},{"id":"9M7Lh6pbJT0","title":"OFFLINETV BOAT FLOAT CHALLENGE","categoryId":"20","channelId":"UCDK9qD5DAQML-pzrtA7A4oA","channelTitle":"OfflineTV","tags":["OfflineTV","Scarra","Poki","Pokimane","Lily","LilyPichu","DisguisedToast","Toast","TwitchTV","Streaming","Vlog","Fail","Epic","Gamers","Streamers","OTV","Michael Reeves","Michael","Reeves","QuarterJade","Masayoshi","Sydeon","OfflineTV boat float","boat float","boat DIY","DIY boat building","boat challenge","build challenge","otv boats","otv boat","offlinetv boat"],"publishedAt":"2023-04-26T21:30:00Z"},{"id":"rML6A8P7q4g","title":"Star Wars Jedi: Survivor - Before You Buy","categoryId":"20","channelId":"UCNvzD7Z-g64bPXxGzaQaa4g","channelTitle":"gameranx","tags":["star wars jedi","star wars jedi survivor","star wars jedi survivor review","jedi survivor review","before you buy jedi survivor","jedi survivor game review","star wars jedi survivor before you buy","jedi survivor ps5 gameplay","jedi survivor performance","star wars jedi survivor game","star wars jedi survivor 60fps","star wars jedi fallen order 2","fallen order 2 review","gameranx","jake baldino","star wars games","cal cestis","jedi survivor game","jedi survivor before you buy"],"publishedAt":"2023-04-26T17:28:19Z"},{"id":"f5wNWAassqg","title":"Picks 1-10: Multiple Quarterbacks & Trades! | 2023 NFL Draft","categoryId":"17","channelId":"UCDVYQ4Zhbm3S2dlz7P1GBDg","channelTitle":"NFL","publishedAt":"2023-04-28T02:21:11Z"},{"id":"70dS-T5p07U","title":"Funniest Animals On The Internet!","categoryId":"24","channelId":"UCUaT_39o1x6qWjz7K2pWcgw","channelTitle":"Beast Reacts","tags":["life hacks","crafts","slime","do it yourself","diy","lifehacks","dily projects","useful things","how to","experiment","experiments","diy activities","handcraft","prank","funny","challenge","pranks","secret","diy slime","laugh","new","skills","tricks","tips","fun"],"publishedAt":"2023-04-25T20:00:03Z"},{"id":"BL_F-oWd7kg","title":"I Spent 100 Days in REAL PIRATE Minecraft","categoryId":"20","channelId":"UCk56ama_RvUkMzexS8I9SIQ","channelTitle":"Branzy","publishedAt":"2023-04-26T19:00:04Z"},{"id":"rR9wkWS9zMk","title":"I Bought the Most Expensive Electric Motorcycle on Amazon","categoryId":"2","channelId":"UCEbCRO739v3_RDmv6_aw1QQ","channelTitle":"Bikes and Beards","tags":["bikes and beards","sean","caleb","motorcycles","srkcycles","srk","beards","bikes"],"publishedAt":"2023-04-28T12:53:49Z"},{"id":"aOTz0Ol8fLA","title":"The Pros and Cons of Every Motorcycle Engine Type","categoryId":"2","channelId":"UCNSMdQtn1SuFzCZjfK2C7dQ","channelTitle":"FortNine","publishedAt":"2023-04-27T15:00:01Z"},{"id":"aOL0UZEr58s","title":"UNHhhh ep 201 - Theft","categoryId":"24","channelId":"UCUUUpaMp8DV6KUOfQwoIiLg","channelTitle":"WOWPresents","tags":["world of wonder","world of wonder productions","wow report","wow presents","wow presents plus","wow pp","wowpp","rupaul's drag race","drag race","unh","unhhhh","season","eight","trixie","mattel","katya","zamo","zamolodchikova","episode","201","theft","art","illusion","security"],"publishedAt":"2023-04-26T19:00:03Z"},{"id":"5vbNvTci_qw","title":"Cambridge Students Try Korean Instant Noodles for the First Time!","categoryId":"23","channelId":"UCg-p3lQIqmhh7gHpyaOmOiQ","channelTitle":"영국남자 Korean Englishman","tags":["Korean","영국남자","영국","조쉬","올리","Josh","Ollie","KoreanEnglish","English","Man","englishman","food","음식","외국인","반응","영상","웃긴","남자","외국","도전","매운","조니","조엘","신부님","크리스","올리아빠","해물","치킨","삼겹살","korean","BBQ","fried","chicken","라면","불닭볶음면","미친남자"],"publishedAt":"2023-04-26T11:42:20Z"},{"id":"2EMZzW7hj0M","title":"I Played Zelda: Tears of the Kingdom (Hands-On Preview)","categoryId":"20","channelId":"UCudx6plmpbs5WtWvsvu-EdQ","channelTitle":"Zeltik","tags":["Zelda"],"publishedAt":"2023-04-26T13:00:02Z"},{"id":"Z0JvYF0WF1o","title":"Food Theory: Blue Raspberry is a Complete LIE!","categoryId":"26","channelId":"UCHYoe8kQ-7Gn9ASOlmI0k6Q","channelTitle":"The Food Theorists","tags":["Blue","blue raspberry","blue food","blue drinks","blue raspberry prime","prime","prime blue raspberry","blue raspberry prime drink","blue raspberry slushie","sour patch kids","blue raspberry jolly rancher","what is blue raspberry","jolly rancher blue","truth about blue raspberry","artificial flavor","artificial flavors","do blue raspberries exist","food facts","food history","blue number 2","blue flavor","ICEE","raspberries","cool blue gatorade","gatorade","food theory","food theorists","matpat"],"publishedAt":"2023-04-25T19:05:16Z"},{"id":"pRH5u5lpArQ","title":"NEXT GOAL WINS | Official Trailer | Searchlight Pictures","categoryId":"1","channelId":"UCor9rW6PgxSQ9vUPWQdnaYQ","channelTitle":"SearchlightPictures","tags":["Next Goal Wins","Next Goal Wins Trailer","Next Goal Wins movie","Searchlight","fox searchlight","searchlight pictures","trailer","official trailer","Movie","Film","Michael Fassbender","Elisabeth Moss","Oscar Kightley","Uli Latukefu","Rachel House","Kaimana","David Fane","Beulah Koale","Chris Alosio","Taika Waititi","Will Arnett","Rhys Darby","soccer","FIFA","American Samoa soccer team","world cup"],"publishedAt":"2023-04-26T20:00:13Z"},{"id":"ezlLyyrUWCU","title":"Manchester City 4-1 Arsenal | Shocking Performance! (Robbie)","categoryId":"17","channelId":"UCBTy8j2cPy6zw68godcE7MQ","channelTitle":"AFTV","tags":["afc","aftv","arsenal","arsenal fan tv","fan cams","arsenal tv","arsenal fan cams","gooners","premier league","robbie lyle","troopz","aftvmedia","martinelli","arteta","mikel arteta","aftv news","transfer daily","gabriel","aftv troopz","arsenal stream","arsenal watch along","bukayo saka","emile smith rowe","emirates stadium","football","soccer","sport","transfers","gabriel jesus","gunners","arsenal fc","Fabio Vieira","transfer window","Oleksandr Zinchenko","Title Race","Man City","Pep","Haaland"],"publishedAt":"2023-04-26T22:13:54Z"},{"id":"qrYMBmmtyfo","title":"VLOG | MY FIRST SHOOT POST BABY & BAMBI'S FIRST HOLIDAY | MOLLYMAE | LOOKFANTASTIC AD","categoryId":"22","channelId":"UC-F3kTU4V680v550AavEOsQ","channelTitle":"MollyMae","publishedAt":"2023-04-26T17:15:07Z"},{"id":"4Uy7pDJ6oVE","title":"FIGHT HIGHLIGHTS | Gervonta \"Tank\" Davis vs. Ryan Garcia","categoryId":"17","channelId":"UCurvRE5fGcdUgCYWgh-BDsg","channelTitle":"DAZN Boxing","tags":["dazn","boxing","highlights","full fight","ko","knockout","top 10","The DAZN Boxing Show","Pelea","Boxeo","Pugile","dazn boxing","Garcia","Garvia davis","Tank Garcia","Ryan Garcia","Tank Davis","Gervonta davis","Full fight","Fight highlights","Showtime","Showtime boxing","Body shot"],"publishedAt":"2023-04-23T05:19:36Z"},{"id":"khP047JyVXM","title":"Armored Core VI Fires of Rubicon - Gameplay Trailer | PS5 & PS4 Games","categoryId":"20","channelId":"UC-2Y8dQb0S6DtpxNgAKoJKA","channelTitle":"PlayStation","tags":["Armored core","armored core vi","fires of rubicon","ACVI","fromsoftware","from software","fromsoft","playstation","mecha game","mecha","rpg","playstation 4","playstation 5","ps4","ps5","video game","miyazaki"],"publishedAt":"2023-04-27T14:00:25Z"},{"id":"3D4sYCf1VPI","title":"Apex Legends: Arsenal Launch Trailer","categoryId":"20","channelId":"UC0ZV6M2THA81QT9hrVWJG3A","channelTitle":"Apex Legends","tags":["apex legends","apex","apex legends trailer","apex trailer","apex legends season 17","apex legends season 17 trailer","apex legends arsenal","apex season 17","エーペックス","apex トレーラー","apex season 17 trailer","apex arsenal","ballistic apex legends","apex legends ballistic","ballistic apex","apex ballistic","new apex trailer","apex legends arsenal launch trailer","arsenal launch trailer","arsenal trailer","arsenal apex legends","respawn apex legends","battle royale","respawn entertainment"],"publishedAt":"2023-04-26T15:00:06Z"},{"id":"B9rBN4UtkWQ","title":"UPDATE: Ed Sheeran vs Marvin Gaye Lawsuit","categoryId":"10","channelId":"UCJquYOG5EL82sKTfH9aMA9Q","channelTitle":"Rick Beato","tags":["rick beato","everything music","rick","beato","music","music theory","music production","education"],"publishedAt":"2023-04-26T18:34:08Z"}]}